mongohelper/AutoIncrementCollection.py
mongohelper/Collection.py
mongohelper/FindQueries.py
mongohelper/MongoDB.py
mongohelper/MongoError.py
mongohelper/ObjectIdCollection.py
mongohelper/UpdateQueries.py
mongohelper/__init__.py
mongohelper-0.0.11.dist-info/DESCRIPTION.rst
mongohelper-0.0.11.dist-info/METADATA
mongohelper-0.0.11.dist-info/RECORD
mongohelper-0.0.11.dist-info/WHEEL
mongohelper-0.0.11.dist-info/metadata.json
mongohelper-0.0.11.dist-info/top_level.txt
